msort/__init__.py
msort/__main__.py
msort/ast_functions.py
msort/config_loader.py
msort/configs.py
msort/cst_functions.py
msort/decorators.py
msort/diff.py
msort/edge_cases.py
msort/formatting.py
msort/generic_functions.py
msort/imports.py
msort/logger.py
msort/main.py
msort/method_describers.py
msort/msort_decorator.py
msort/utilities.py
msort-0.1.9.dist-info/LICENSE
msort-0.1.9.dist-info/METADATA
msort-0.1.9.dist-info/WHEEL
msort-0.1.9.dist-info/entry_points.txt
msort-0.1.9.dist-info/top_level.txt
msort-0.1.9.dist-info/RECORD
