Metadata-Version: 2.1
Name: msort
Version: 0.1.9
Summary: Automatic ordering of Python class components.
Author-email: Isaac Kitchen-Smith <isaacks123@gmail.com>
Keywords: msort
Classifier: Operating System :: OS Independent
Classifier: Programming Language :: Python
Classifier: Programming Language :: Python :: 3
Classifier: Intended Audience :: Developers
Classifier: Typing :: Typed
Requires-Python: >=3.9
License-File: LICENSE
Requires-Dist: ast-comments ==1.2.2
Requires-Dist: astor ==0.8.1
Requires-Dist: libcst ==1.3.1
Requires-Dist: toml ==0.10.2
Provides-Extra: dev
Requires-Dist: black ==24.3.0 ; extra == 'dev'
Requires-Dist: coverage ==6.5.0 ; extra == 'dev'
Requires-Dist: mypy ==1.9.0 ; extra == 'dev'
Requires-Dist: pre-commit ==3.7.0 ; extra == 'dev'
Requires-Dist: pytest ==8.1.2 ; extra == 'dev'
Requires-Dist: pytest-cov ==5.0.0 ; extra == 'dev'
Requires-Dist: tox ==4.15.0 ; extra == 'dev'
Requires-Dist: validate-pyproject[all] ; extra == 'dev'
